pycommon/__init__.py
pycommon/auth/__init__.py
pycommon/auth/jwt/__init__.py
pycommon/auth/jwt/jwt_bearer.py
pycommon/auth/jwt/tests/__init__.py
pycommon/auth/jwt/tests/test_jwt_bearer.py
pycommon/utils/__init__.py
pycommon/utils/result.py
pycommon_kit_dev-0.0.1.dist-info/METADATA
pycommon_kit_dev-0.0.1.dist-info/WHEEL
pycommon_kit_dev-0.0.1.dist-info/top_level.txt
pycommon_kit_dev-0.0.1.dist-info/RECORD
