Metadata-Version: 2.1
Name: pycommon-kit-dev
Version: 0.0.1
Summary: Common solution for development.
Home-page: UNKNOWN
Author: Tomcat (Thomas Buida), AngryDanny (Daniel Nwosu)
Author-email: <4ngry24@gmail.com>
License: UNKNOWN
Keywords: python,common,shared
Platform: UNKNOWN
Classifier: Development Status :: 1 - Planning
Classifier: Intended Audience :: Developers
Classifier: Programming Language :: Python :: 3
Classifier: Operating System :: Unix
Classifier: Operating System :: MacOS :: MacOS X
Classifier: Operating System :: Microsoft :: Windows
Requires-Dist: fastapi
Requires-Dist: jose
Requires-Dist: loguru
Requires-Dist: pydantic
Requires-Dist: pytest
